[
  {
    "ticker": "MMS.AX",
    "asx_code": "MMS",
    "price": 15.79,
    "rvol": 2.1,
    "atr_pct": 2.62,
    "atr_value": 0.4139,
    "volume_velocity": 1.72,
    "is_trending": true,
    "market_cap": 1099663360,
    "vwap": 14.4906,
    "vwap_distance_pct": 8.97,
    "vwap_position": "above",
    "gap_up": true,
    "gap_pct": 2.01,
    "vwap_multiplier": 1.2,
    "gap_bonus": 1.5,
    "score": 184.5,
    "pulse_score": 0.23,
    "passes_filters": true,
    "filters": {
      "rvol": true,
      "atr": true,
      "trend": true,
      "cr": true
    },
    "recent_volume": 560862.0,
    "cr_ratio": 0.95,
    "scanned_at": "2026-04-08T08:16:53.937284",
    "sentiment_score": 1.0,
    "sentiment_posts": 78,
    "momentum_score": 184.5
  },
  {
    "ticker": "QAN.AX",
    "asx_code": "QAN",
    "price": 9.29,
    "rvol": 2.18,
    "atr_pct": 3.8,
    "atr_value": 0.3532,
    "volume_velocity": 1.77,
    "is_trending": true,
    "market_cap": 14057620480,
    "vwap": 8.5584,
    "vwap_distance_pct": 8.55,
    "vwap_position": "above",
    "gap_up": true,
    "gap_pct": 8.36,
    "vwap_multiplier": 1.2,
    "gap_bonus": 1.5,
    "score": 170.13,
    "pulse_score": 0.25,
    "passes_filters": true,
    "filters": {
      "rvol": true,
      "atr": true,
      "trend": true,
      "cr": true
    },
    "recent_volume": 19637690.0,
    "cr_ratio": 0.75,
    "scanned_at": "2026-04-08T08:17:13.415448",
    "sentiment_score": 1.0,
    "sentiment_posts": 82,
    "momentum_score": 170.13
  },
  {
    "ticker": "AAI.AX",
    "asx_code": "AAI",
    "price": 105.65,
    "rvol": 1.74,
    "atr_pct": 3.83,
    "atr_value": 4.0436,
    "volume_velocity": 1.48,
    "is_trending": true,
    "market_cap": 29961125888,
    "vwap": 91.0882,
    "vwap_distance_pct": 15.99,
    "vwap_position": "above",
    "gap_up": false,
    "gap_pct": 1.71,
    "vwap_multiplier": 1.2,
    "gap_bonus": 1.0,
    "score": 117.26,
    "pulse_score": 0.12,
    "passes_filters": true,
    "filters": {
      "rvol": true,
      "atr": true,
      "trend": true,
      "cr": true
    },
    "recent_volume": 408296.0,
    "cr_ratio": 0.69,
    "scanned_at": "2026-04-08T08:16:02.099238",
    "sentiment_score": 1.0,
    "sentiment_posts": 76,
    "momentum_score": 117.26
  },
  {
    "ticker": "KGN.AX",
    "asx_code": "KGN",
    "price": 4.11,
    "rvol": 1.84,
    "atr_pct": 3.96,
    "atr_value": 0.1629,
    "volume_velocity": 1.9,
    "is_trending": true,
    "market_cap": 395880352,
    "vwap": 3.7495,
    "vwap_distance_pct": 9.61,
    "vwap_position": "above",
    "gap_up": false,
    "gap_pct": -0.51,
    "vwap_multiplier": 1.2,
    "gap_bonus": 1.0,
    "score": 115.46,
    "pulse_score": 0.24,
    "passes_filters": true,
    "filters": {
      "rvol": true,
      "atr": true,
      "trend": true,
      "cr": true
    },
    "recent_volume": 652524.0,
    "cr_ratio": 0.9,
    "scanned_at": "2026-04-08T08:16:50.668787",
    "sentiment_score": 1.0,
    "sentiment_posts": 76,
    "momentum_score": 115.46
  }
]